[
  {
    "test_name": "ホワイト(B)決定結果",
    "big_r": 107,
    "big_g": 107,
    "big_b": 107,
    "big_r_per": 14.796875,
    "big_g_per": 14.796875,
    "big_b_per": 14.796875,
    "target_r": 107,
    "target_g": 107,
    "target_b": 107,
    "target_r_per": 14.796875,
    "target_g_per": 14.796875,
    "target_b_per": 14.796875,
    "time": 4.07
  },
  {
    "test_name": "ホワイト(RG)決定結果",
    "big_r": 124,
    "big_g": 124,
    "big_b": 107,
    "big_r_per": 20.46875,
    "big_g_per": 20.46875,
    "big_b_per": 14.796875,
    "target_r": 124,
    "target_g": 124,
    "target_b": 107,
    "target_r_per": 20.46875,
    "target_g_per": 20.46875,
    "target_b_per": 14.796875,
    "time": 2.38
  },
  {
    "test_name": "緑色視感度測定結果",
    "big_r": 107,
    "big_g": 107,
    "big_b": 107,
    "big_r_per": 14.796875,
    "big_g_per": 14.796875,
    "big_b_per": 14.796875,
    "target_r": 107,
    "target_g": 102,
    "target_b": 107,
    "target_r_per": 14.796875,
    "target_g_per": 13.3203125,
    "target_b_per": 14.796875,
    "time": 2.13
  },
  {
    "test_name": "赤色視感度測定結果",
    "big_r": 107,
    "big_g": 107,
    "big_b": 107,
    "big_r_per": 14.796875,
    "big_g_per": 14.796875,
    "big_b_per": 14.796875,
    "target_r": 96,
    "target_g": 107,
    "target_b": 107,
    "target_r_per": 11.65625,
    "target_g_per": 14.796875,
    "target_b_per": 14.796875,
    "time": 2.18
  },
  {
    "test_name": "青色視感度測定結果",
    "big_r": 107,
    "big_g": 107,
    "big_b": 107,
    "big_r_per": 14.796875,
    "big_g_per": 14.796875,
    "big_b_per": 14.796875,
    "target_r": 107,
    "target_g": 107,
    "target_b": 99,
    "target_r_per": 14.796875,
    "target_g_per": 14.796875,
    "target_b_per": 12.4765625,
    "time": 2.47
  },
  {
    "test_name": "赤緑視感度測定結果",
    "big_r": 107,
    "big_g": 107,
    "big_b": 107,
    "big_r_per": 14.796875,
    "big_g_per": 14.796875,
    "big_b_per": 14.796875,
    "target_r": 94,
    "target_g": 94,
    "target_b": 107,
    "target_r_per": 11.1328125,
    "target_g_per": 11.1328125,
    "target_b_per": 14.796875,
    "time": 1.4
  }
]